ffdd/__init__.py
ffdd/__main__.py
ffdd-0.0.4.dist-info/entry_points.txt
ffdd-0.0.4.dist-info/WHEEL
ffdd-0.0.4.dist-info/METADATA
ffdd-0.0.4.dist-info/RECORD
